dsm2dtm/__init__.py
dsm2dtm/algorithm.py
dsm2dtm/constants.py
dsm2dtm/core.py
dsm2dtm/utm_utils.py
dsm2dtm-0.3.1.dist-info/licenses/LICENSE
dsm2dtm-0.3.1.dist-info/METADATA
dsm2dtm-0.3.1.dist-info/WHEEL
dsm2dtm-0.3.1.dist-info/entry_points.txt
dsm2dtm-0.3.1.dist-info/top_level.txt
dsm2dtm-0.3.1.dist-info/RECORD
