Metadata-Version: 2.4
Name: dsm2dtm
Version: 0.3.1
Summary: Generate DTM (Digital Terrain Model) from DSM (Digital Surface Model)
Author-email: Naman Jain <naman.jain@btech2015.iitgn.ac.in>
Project-URL: Homepage, https://github.com/seedlit/dsm2dtm
Classifier: Programming Language :: Python :: 3
Classifier: Programming Language :: Python :: 3.11
Classifier: Programming Language :: Python :: 3.12
Classifier: Programming Language :: Python :: 3.13
Classifier: Programming Language :: Python :: 3.14
Classifier: License :: OSI Approved :: MIT License
Classifier: Operating System :: OS Independent
Classifier: Topic :: Scientific/Engineering
Classifier: Intended Audience :: Developers
Classifier: Intended Audience :: Education
Classifier: Intended Audience :: Science/Research
Classifier: Development Status :: 4 - Beta
Requires-Python: >=3.11
License-File: LICENSE
Requires-Dist: numpy
Requires-Dist: rasterio
Requires-Dist: scipy
Requires-Dist: scikit-image
Requires-Dist: pyproj
Provides-Extra: test
Requires-Dist: pytest; extra == "test"
Provides-Extra: dev
Requires-Dist: ruff; extra == "dev"
Requires-Dist: mypy; extra == "dev"
Requires-Dist: pre-commit; extra == "dev"
Requires-Dist: pooch; extra == "dev"
Dynamic: license-file
